pypcd/__init__.py
pypcd/nea_pc_format.py
pypcd/numpy_pc2.py
pypcd/pdutil.py
pypcd/pypcd.py
pypcd/sautil.py
pypcd2/__init__.py
pypcd2/pdutil.py
pypcd2/pypcd.py
pypcd2/sautil.py
pypcd2-0.2.1.dist-info/LICENSE
pypcd2-0.2.1.dist-info/METADATA
pypcd2-0.2.1.dist-info/WHEEL
pypcd2-0.2.1.dist-info/top_level.txt
pypcd2-0.2.1.dist-info/RECORD
