Metadata-Version: 2.1
Name: pypcd2
Version: 0.2.1
Summary: Read and write PCL .pcd files in python. Forked from https://github.com/dimatura/pypcd/
Home-page: https://github.com/bochent/pypcd2/
Author: tongbochen
Author-email: bochen.tong@outlook.com
License: BSD license
Keywords: pypcd2
Platform: UNKNOWN
Classifier: Development Status :: 2 - Pre-Alpha
Classifier: Intended Audience :: Science/Research
Classifier: License :: OSI Approved :: BSD License
Classifier: Natural Language :: English
Classifier: Programming Language :: Python :: 2
Classifier: Programming Language :: Python :: 2.7
Classifier: Topic :: Scientific/Engineering
Classifier: Topic :: Scientific/Engineering :: Artificial Intelligence
Classifier: Topic :: Multimedia :: Graphics :: 3D Modeling
Classifier: Topic :: Multimedia :: Graphics :: Capture
Classifier: Topic :: Multimedia :: Graphics :: Graphics Conversion
License-File: LICENSE
Requires-Dist: numpy
Requires-Dist: python-lzf
